Antlr4JianmingJiaocheng/README.md
Antlr4JianmingJiaocheng/__init__.py
Antlr4JianmingJiaocheng/__main__.py
Antlr4JianmingJiaocheng/file.epub
Antlr4JianmingJiaocheng/index.html
Antlr4JianmingJiaocheng/css/__init__.py
Antlr4JianmingJiaocheng/css/annotations.css
Antlr4JianmingJiaocheng/css/main.css
Antlr4JianmingJiaocheng/css/normalize.css
Antlr4JianmingJiaocheng/css/popup.css
Antlr4JianmingJiaocheng/font/__init__.py
Antlr4JianmingJiaocheng/font/fontello.eot
Antlr4JianmingJiaocheng/font/fontello.svg
Antlr4JianmingJiaocheng/font/fontello.ttf
Antlr4JianmingJiaocheng/font/fontello.woff
Antlr4JianmingJiaocheng/img/__init__.py
Antlr4JianmingJiaocheng/img/annotator-glyph-sprite.png
Antlr4JianmingJiaocheng/img/annotator-icon-sprite.png
Antlr4JianmingJiaocheng/img/apple-touch-icon.png
Antlr4JianmingJiaocheng/img/cancelfullscreen.png
Antlr4JianmingJiaocheng/img/close.png
Antlr4JianmingJiaocheng/img/fullscreen.png
Antlr4JianmingJiaocheng/img/loader.gif
Antlr4JianmingJiaocheng/img/menu-icon.png
Antlr4JianmingJiaocheng/img/save.png
Antlr4JianmingJiaocheng/img/saved.png
Antlr4JianmingJiaocheng/img/settings-s.png
Antlr4JianmingJiaocheng/img/settings.png
Antlr4JianmingJiaocheng/img/star.png
Antlr4JianmingJiaocheng/js/__init__.py
Antlr4JianmingJiaocheng/js/epub.js
Antlr4JianmingJiaocheng/js/epub.min.js
Antlr4JianmingJiaocheng/js/epub.min.map
Antlr4JianmingJiaocheng/js/hooks.min.js
Antlr4JianmingJiaocheng/js/hooks.min.map
Antlr4JianmingJiaocheng/js/reader.js
Antlr4JianmingJiaocheng/js/reader.js.map
Antlr4JianmingJiaocheng/js/reader.min.js
Antlr4JianmingJiaocheng/js/reader.min.map
Antlr4JianmingJiaocheng/js/hooks/__init__.py
Antlr4JianmingJiaocheng/js/hooks/extensions/__init__.py
Antlr4JianmingJiaocheng/js/hooks/extensions/highlight.js
Antlr4JianmingJiaocheng/js/libs/__init__.py
Antlr4JianmingJiaocheng/js/libs/jquery.min.js
Antlr4JianmingJiaocheng/js/libs/localforage.min.js
Antlr4JianmingJiaocheng/js/libs/screenfull.js
Antlr4JianmingJiaocheng/js/libs/screenfull.min.js
antlr_4_jianming_jiaocheng-2024.3.3.0.dist-info/METADATA
antlr_4_jianming_jiaocheng-2024.3.3.0.dist-info/WHEEL
antlr_4_jianming_jiaocheng-2024.3.3.0.dist-info/entry_points.txt
antlr_4_jianming_jiaocheng-2024.3.3.0.dist-info/top_level.txt
antlr_4_jianming_jiaocheng-2024.3.3.0.dist-info/RECORD
